{
  "message": "request.response",
  "properties": {
    "response": {
      "output": "There have been several notable incidents involving submarines in recent years. One such incident involves the Virginia-class submarine, which is a class of nuclear-powered fast attack submarines used by the United States Navy. These submarines have been involved in various operations and exercises around the world.\n\nAnother incident that gained attention was the release of the 2013 film \"Phantom,\" which revolves around a Soviet submarine during the Cold War era. While the film is fictional, it highlights the dangers and challenges that submariners face while operating"
    },
    "source": "DEMO_REPLAYS"
  }
}
